asxshorts/__init__.py
asxshorts/adapters.py
asxshorts/cache.py
asxshorts/cli.py
asxshorts/client.py
asxshorts/errors.py
asxshorts/models.py
asxshorts/parse.py
asxshorts/py.typed
asxshorts/resolve.py
asxshorts-0.1.1.dist-info/METADATA
asxshorts-0.1.1.dist-info/WHEEL
asxshorts-0.1.1.dist-info/entry_points.txt
asxshorts-0.1.1.dist-info/licenses/LICENSE
asxshorts-0.1.1.dist-info/RECORD
