Metadata-Version: 2.4
Name: asxshorts
Version: 0.1.1
Summary: Lightweight Python client to download official ASX short position daily CSVs with local caching
Project-URL: Homepage, https://github.com/ay-mich/asxshorts
Project-URL: Documentation, https://ay-mich.github.io/asxshorts/asxshorts.html
Project-URL: Repository, https://github.com/ay-mich/asxshorts
Project-URL: Issues, https://github.com/ay-mich/asxshorts/issues
Project-URL: Changelog, https://github.com/ay-mich/asxshorts/blob/main/CHANGELOG.md
Author-email: ay-mich <aydenmich@gmail.com>
Maintainer-email: ay-mich <aydenmich@gmail.com>
License: MIT
License-File: LICENSE
Keywords: asx,australia,csv,data,finance,short-selling
Classifier: Development Status :: 4 - Beta
Classifier: Intended Audience :: Developers
Classifier: Intended Audience :: Financial and Insurance Industry
Classifier: License :: OSI Approved :: MIT License
Classifier: Operating System :: OS Independent
Classifier: Programming Language :: Python :: 3
Classifier: Programming Language :: Python :: 3.11
Classifier: Programming Language :: Python :: 3.12
Classifier: Programming Language :: Python :: 3.13
Classifier: Topic :: Office/Business :: Financial
Classifier: Topic :: Software Development :: Libraries :: Python Modules
Classifier: Typing :: Typed
Requires-Python: >=3.11
Requires-Dist: pydantic-settings>=2.0.0
Requires-Dist: pydantic>=2.0.0
Requires-Dist: python-dateutil>=2.9.0
Requires-Dist: requests>=2.32.0
Requires-Dist: rich>=13.0.0
Requires-Dist: typer>=0.12.0
Provides-Extra: all
Requires-Dist: bandit>=1.7.5; extra == 'all'
Requires-Dist: bandit>=1.8.6; extra == 'all'
Requires-Dist: build>=1.0.0; extra == 'all'
Requires-Dist: commitizen>=3.13.0; extra == 'all'
Requires-Dist: mkdocs-material>=9.5.0; extra == 'all'
Requires-Dist: mkdocs>=1.5.0; extra == 'all'
Requires-Dist: mkdocstrings[python]>=0.24.0; extra == 'all'
Requires-Dist: mypy>=1.8.0; extra == 'all'
Requires-Dist: pandas>=2.0.0; extra == 'all'
Requires-Dist: pdoc>=15.0.4; extra == 'all'
Requires-Dist: pip-audit>=2.9.0; extra == 'all'
Requires-Dist: polars>=1.0.0; extra == 'all'
Requires-Dist: pre-commit>=3.6.0; extra == 'all'
Requires-Dist: pre-commit>=4.3.0; extra == 'all'
Requires-Dist: pydocstyle>=6.3.0; extra == 'all'
Requires-Dist: pytest-asyncio>=0.23.0; extra == 'all'
Requires-Dist: pytest-cov>=4.0.0; extra == 'all'
Requires-Dist: pytest-mock>=3.12.0; extra == 'all'
Requires-Dist: pytest>=8.0.0; extra == 'all'
Requires-Dist: ruff>=0.14.1; extra == 'all'
Requires-Dist: ruff>=0.6.0; extra == 'all'
Requires-Dist: safety>=2.3.5; extra == 'all'
Requires-Dist: twine>=5.0.0; extra == 'all'
Requires-Dist: twine>=6.2.0; extra == 'all'
Requires-Dist: types-python-dateutil>=2.9.0; extra == 'all'
Requires-Dist: types-requests>=2.32.0; extra == 'all'
Requires-Dist: vulture>=2.14; extra == 'all'
Provides-Extra: dev
Requires-Dist: bandit>=1.7.5; extra == 'dev'
Requires-Dist: bandit>=1.8.6; extra == 'dev'
Requires-Dist: build>=1.0.0; extra == 'dev'
Requires-Dist: commitizen>=3.13.0; extra == 'dev'
Requires-Dist: mypy>=1.8.0; extra == 'dev'
Requires-Dist: pdoc>=15.0.4; extra == 'dev'
Requires-Dist: pip-audit>=2.9.0; extra == 'dev'
Requires-Dist: pre-commit>=3.6.0; extra == 'dev'
Requires-Dist: pre-commit>=4.3.0; extra == 'dev'
Requires-Dist: pydocstyle>=6.3.0; extra == 'dev'
Requires-Dist: pytest-asyncio>=0.23.0; extra == 'dev'
Requires-Dist: pytest-cov>=4.0.0; extra == 'dev'
Requires-Dist: pytest-mock>=3.12.0; extra == 'dev'
Requires-Dist: pytest>=8.0.0; extra == 'dev'
Requires-Dist: ruff>=0.14.1; extra == 'dev'
Requires-Dist: ruff>=0.6.0; extra == 'dev'
Requires-Dist: safety>=2.3.5; extra == 'dev'
Requires-Dist: twine>=5.0.0; extra == 'dev'
Requires-Dist: twine>=6.2.0; extra == 'dev'
Requires-Dist: types-python-dateutil>=2.9.0; extra == 'dev'
Requires-Dist: types-requests>=2.32.0; extra == 'dev'
Requires-Dist: vulture>=2.14; extra == 'dev'
Provides-Extra: docs
Requires-Dist: mkdocs-material>=9.5.0; extra == 'docs'
Requires-Dist: mkdocs>=1.5.0; extra == 'docs'
Requires-Dist: mkdocstrings[python]>=0.24.0; extra == 'docs'
Provides-Extra: pandas
Requires-Dist: pandas>=2.0.0; extra == 'pandas'
Provides-Extra: polars
Requires-Dist: polars>=1.0.0; extra == 'polars'
